absscpi/__init__.py
absscpi/client.py
absscpi-1.1.0.dist-info/METADATA
absscpi-1.1.0.dist-info/WHEEL
absscpi-1.1.0.dist-info/licenses/LICENSE
absscpi-1.1.0.dist-info/RECORD
