Metadata-Version: 2.4
Name: absscpi
Version: 1.1.0
Summary: SCPI driver for the Bloomy Controls Advanced Battery Simulator
Project-URL: homepage, https://github.com/BloomyControls/abs-scpi-driver-python
Project-URL: source, https://github.com/BloomyControls/abs-scpi-driver-python
Project-URL: issues, https://github.com/BloomyControls/abs-scpi-driver-python/issues
Project-URL: documentation, https://bloomycontrols.github.io/abs-scpi-driver-python
Author: Bloomy Controls, Inc.
License: Copyright (c) 2024, Bloomy Controls, Inc. All rights reserved.
License-File: LICENSE
Classifier: License :: OSI Approved :: BSD License
Classifier: Operating System :: Microsoft :: Windows
Classifier: Operating System :: POSIX :: Linux
Classifier: Programming Language :: Python :: 3
Classifier: Programming Language :: Python :: 3 :: Only
Classifier: Programming Language :: Python :: 3.8
Classifier: Programming Language :: Python :: 3.9
Classifier: Programming Language :: Python :: 3.10
Classifier: Programming Language :: Python :: 3.11
Classifier: Programming Language :: Python :: 3.12
Classifier: Programming Language :: Python :: Implementation :: CPython
Requires-Python: >=3.8
